<?xml version="1.0"?>
<!DOCTYPE softwarelist SYSTEM "softwarelist.dtd">
<!-- Number of items in this list = 16 -->
<softwarelist name="smc777_quik" description="smc777_quik loose roms">
	<software name="smcdc46dcfc4b9e9">
		<description>Deepspace</description>
		<year>????</year>
		<publisher>unknown</publisher>
		<part name="quik" interface="smc777_quik">
			<dataarea name="quik" size="8956">
				<rom name="Deepspace.com" size="8956" crc="e6a18666" sha1="dc46dcfc4b9e9ea2abcc09d1535ab742b3948117"/>
			</dataarea>
		</part>
	</software>
	<software name="smc4e0eaf06e062b">
		<description>Deepspace_CPM</description>
		<year>????</year>
		<publisher>unknown</publisher>
		<part name="quik" interface="smc777_quik">
			<dataarea name="quik" size="9594">
				<rom name="Deepspace_CPM.com" size="9594" crc="3a1a3e9c" sha1="4e0eaf06e062b616844b9028065f24acb888ef74"/>
			</dataarea>
		</part>
	</software>
	<software name="smcb77a89aa30166">
		<description>Elite Planet Browser</description>
		<year>????</year>
		<publisher>unknown</publisher>
		<part name="quik" interface="smc777_quik">
			<dataarea name="quik" size="14017">
				<rom name="Elite Planet Browser.com" size="14017" crc="26f3e933" sha1="b77a89aa30166b325fdfe93bc254e83bdcde1b69"/>
			</dataarea>
		</part>
	</software>
	<software name="smc8cf3bd894bf94">
		<description>Elite Planet Browser_CPM</description>
		<year>????</year>
		<publisher>unknown</publisher>
		<part name="quik" interface="smc777_quik">
			<dataarea name="quik" size="19156">
				<rom name="Elite Planet Browser_CPM.com" size="19156" crc="ceee663d" sha1="8cf3bd894bf942baef5e1b6bdf2757c643c65ee5"/>
			</dataarea>
		</part>
	</software>
	<software name="smc0cf79d5dd07ae">
		<description>Ghost City</description>
		<year>????</year>
		<publisher>unknown</publisher>
		<part name="quik" interface="smc777_quik">
			<dataarea name="quik" size="10752">
				<rom name="Ghost City.com" size="10752" crc="ba6a2ab8" sha1="0cf79d5dd07ae82b0b74c8d1a3234abd9329859b"/>
			</dataarea>
		</part>
	</software>
	<software name="smc84fbad6e7b0a3">
		<description>H-Tron</description>
		<year>????</year>
		<publisher>unknown</publisher>
		<part name="quik" interface="smc777_quik">
			<dataarea name="quik" size="8650">
				<rom name="H-Tron.com" size="8650" crc="dd0bc4f4" sha1="84fbad6e7b0a37f322eeddc3cdef96e766b942d3"/>
			</dataarea>
		</part>
	</software>
	<software name="smcb31945c35b33d">
		<description>H-Tron_CPM</description>
		<year>????</year>
		<publisher>unknown</publisher>
		<part name="quik" interface="smc777_quik">
			<dataarea name="quik" size="13701">
				<rom name="H-Tron_CPM.com" size="13701" crc="c73bdcbd" sha1="b31945c35b33d3d729480a74f90c3b4936e28118"/>
			</dataarea>
		</part>
	</software>
	<software name="smc93cb306a0b60d">
		<description>HETZER</description>
		<year>????</year>
		<publisher>unknown</publisher>
		<part name="quik" interface="smc777_quik">
			<dataarea name="quik" size="51840">
				<rom name="HETZER.COM" size="51840" crc="0c22da1b" sha1="93cb306a0b60db4484413016adcff0db9c3542d1"/>
			</dataarea>
		</part>
	</software>
	<software name="smcda07fd57c34be">
		<description>MastermindRK</description>
		<year>????</year>
		<publisher>unknown</publisher>
		<part name="quik" interface="smc777_quik">
			<dataarea name="quik" size="8391">
				<rom name="MastermindRK.com" size="8391" crc="378136f5" sha1="da07fd57c34bedfc03e4c5aa863eedfcb9c22541"/>
			</dataarea>
		</part>
	</software>
	<software name="smce2579fc570501">
		<description>MastermindRK_CPM</description>
		<year>????</year>
		<publisher>unknown</publisher>
		<part name="quik" interface="smc777_quik">
			<dataarea name="quik" size="13153">
				<rom name="MastermindRK_CPM.com" size="13153" crc="268f64e8" sha1="e2579fc57050127a84c94b54c04fc7524b9066a2"/>
			</dataarea>
		</part>
	</software>
	<software name="smc10f6d31e557b0">
		<description>MastermindRK_smc777_CPM(old)</description>
		<year>????</year>
		<publisher>unknown</publisher>
		<part name="quik" interface="smc777_quik">
			<dataarea name="quik" size="12728">
				<rom name="MastermindRK_smc777_CPM(old).com" size="12728" crc="9ce4d89e" sha1="10f6d31e557b0a094205f3676ba13308dac2a875"/>
			</dataarea>
		</part>
	</software>
	<software name="smcba49e74603031">
		<description>Rocker</description>
		<year>????</year>
		<publisher>unknown</publisher>
		<part name="quik" interface="smc777_quik">
			<dataarea name="quik" size="7552">
				<rom name="Rocker.com" size="7552" crc="5501af6c" sha1="ba49e74603031154af8835612a03e0026bff06d6"/>
			</dataarea>
		</part>
	</software>
	<software name="smc621ad5f5006c2">
		<description>Smcpaint</description>
		<year>????</year>
		<publisher>unknown</publisher>
		<part name="quik" interface="smc777_quik">
			<dataarea name="quik" size="18432">
				<rom name="Smcpaint.com" size="18432" crc="521d4545" sha1="621ad5f5006c2bfd796e490a65dd3f874d043f85"/>
			</dataarea>
		</part>
	</software>
	<software name="smc8607597f69c68">
		<description>STRIKER</description>
		<year>????</year>
		<publisher>unknown</publisher>
		<part name="quik" interface="smc777_quik">
			<dataarea name="quik" size="18176">
				<rom name="STRIKER.COM" size="18176" crc="b8bec638" sha1="8607597f69c6804f5927723a07b65c66b88090f9"/>
			</dataarea>
		</part>
	</software>
	<software name="smc0022e66fe0e20">
		<description>STRIKER2</description>
		<year>????</year>
		<publisher>unknown</publisher>
		<part name="quik" interface="smc777_quik">
			<dataarea name="quik" size="22912">
				<rom name="STRIKER2.COM" size="22912" crc="62cec45c" sha1="0022e66fe0e20132bbbe420d45be35b4a45ec54e"/>
			</dataarea>
		</part>
	</software>
	<software name="smcbe181e026b174">
		<description>XOR777</description>
		<year>????</year>
		<publisher>unknown</publisher>
		<part name="quik" interface="smc777_quik">
			<dataarea name="quik" size="4736">
				<rom name="XOR777.COM" size="4736" crc="69b329ac" sha1="be181e026b1742139b50552ba650dd79fbe8829f"/>
			</dataarea>
		</part>
	</software>
</softwarelist>
